ccHBGF/__init__.py
ccHBGF/_adjacency.py
ccHBGF/_orthogonal.py
ccHBGF/_spectral.py
ccHBGF/config.py
ccHBGF/core.py
ccHBGF/py.typed
cchbgf-0.2.0.dist-info/METADATA
cchbgf-0.2.0.dist-info/WHEEL
cchbgf-0.2.0.dist-info/licenses/LICENSE
cchbgf-0.2.0.dist-info/RECORD
