Metadata-Version: 2.4
Name: ccHBGF
Version: 0.2.0
Summary: ccHBGF - consensus clustering using Hybrid Bipartite Graph Formulation (HBGF)
Author: E. H. von Rein
Maintainer: E. H. von Rein
License: MIT
License-File: LICENSE
Classifier: License :: OSI Approved :: MIT License
Classifier: Operating System :: OS Independent
Classifier: Programming Language :: Python :: 3
Requires-Python: >=3.10
Requires-Dist: numba
Requires-Dist: numpy>=2.0
Requires-Dist: scikit-learn
Requires-Dist: scipy
Provides-Extra: docs
Requires-Dist: sphinx; extra == 'docs'
Requires-Dist: sphinx-book-theme; extra == 'docs'
Provides-Extra: tests
Requires-Dist: pytest; extra == 'tests'
Requires-Dist: pytest-cov; extra == 'tests'
Requires-Dist: pytest-xdist; extra == 'tests'
Provides-Extra: tutorial
Requires-Dist: igraph; extra == 'tutorial'
Requires-Dist: ipykernel; extra == 'tutorial'
Requires-Dist: scanpy; extra == 'tutorial'
Requires-Dist: scikit-misc; extra == 'tutorial'
